nonebot_plugin_covid/__init__.py
nonebot_plugin_covid/Covid19_Push/__init__.py
nonebot_plugin_covid/Covid19_Push/draw_covid19.py
nonebot_plugin_covid/Covid19_main/__init__.py
nonebot_plugin_covid/res/__init__.py
nonebot_plugin_covid/util/__init__.py
nonebot_plugin_covid/util/aiorequest.py
nonebot_plugin_covid/util/city_list.py
nonebot_plugin_covid/util/common.py
nonebot_plugin_covid/util/covid_config.py
nonebot_plugin_covid/util/pil_util.py
nonebot_plugin_covid/util/util.py
nonebot_plugin_covid-0.0.6.dist-info/METADATA
nonebot_plugin_covid-0.0.6.dist-info/WHEEL
nonebot_plugin_covid-0.0.6.dist-info/top_level.txt
nonebot_plugin_covid-0.0.6.dist-info/RECORD
